<?xml version="1.0" encoding="UTF-8"?>
<Roles>
  <Objects />
  <Role localize="EasyStudioDeveloper">
    <Disabled>False</Disabled>
    <ReadOnly>True</ReadOnly>
    <Description localizable="true">EasyStudioDeveloper</Description>
    <Grants>
      <Grant>
        <NameSpace>Extensions.EasyBuilder.TbEasyBuilder.NewDocument</NameSpace>
        <TypeId>5</TypeId>
        <GrantValue>1</GrantValue>
        <InheritMask>0</InheritMask>
      </Grant>
      <Grant>
        <NameSpace>Extensions.EasyBuilder.TbEasyBuilder.NewBatchDocument</NameSpace>
        <TypeId>5</TypeId>
        <GrantValue>1</GrantValue>
        <InheritMask>0</InheritMask>
      </Grant>
      <Grant>
        <NameSpace>Extensions.EasyBuilder.TbEasyBuilder.EasyStudioDesigner</NameSpace>
        <TypeId>5</TypeId>
        <GrantValue>1</GrantValue>
        <InheritMask>0</InheritMask>
      </Grant>
      <Grant>
        <NameSpace>Extensions.EasyBuilder.TbEasyBuilder.OpenEasyBuilderSettings</NameSpace>
        <TypeId>3</TypeId>
        <GrantValue>1</GrantValue>
        <InheritMask>0</InheritMask>
      </Grant>
      <Grant>
        <NameSpace>Extensions.EasyBuilder.TbEasyBuilder.OpenMenuEditor</NameSpace>
        <TypeId>3</TypeId>
        <GrantValue>1</GrantValue>
        <InheritMask>0</InheritMask>
      </Grant>
    </Grants>
  </Role>
</Roles>