<?xml version="1.0" encoding="utf-8" standalone="yes"?>
<HotKeyLink>
  <Function namespace="Framework.TbResourcesMng.TbResourcesMng.Resources" localize="Resources" type="string">
	<Param name="ResourceType" type="string" localize="Resource type" />
    <Param name="Enabled" type="integer" localize="0 (Enabled) / 1 (Disabled) / 2 (Both)" />
  </Function>
   <DbField name="RM_Resources.ResourceCode" />
  <ComboBox>
	<Column source="RM_Resources.ResourceCode" />
	<Column source="RM_Resources.Description" />
  </ComboBox>
  <ClassName>HKLResources</ClassName>
</HotKeyLink>





